PyPi_README.rst
README.md
setup.py
py_ev/__init__.py
py_ev/py_ev.py
py_ev.egg-info/PKG-INFO
py_ev.egg-info/SOURCES.txt
py_ev.egg-info/dependency_links.txt
py_ev.egg-info/top_level.txt