Metadata-Version: 2.1
Name: py-ev
Version: 0.0.8
Summary: Poker hand evaluator written and tested in Python
Home-page: https://github.com/JBielan/py_ev
Author: Jakub Bielan
Author-email: jkbielan@gmail.com
License: UNKNOWN
Keywords: poker,hand-evaluator,texas-holdem,omaha,6-plus,evaluator
Platform: UNKNOWN
Requires-Python: >=3
